suiteas/__init__.py
suiteas/__main__.py
suiteas/_version.py
suiteas/config.py
suiteas/domain.py
suiteas/core/__init__.py
suiteas/core/check.py
suiteas/core/enforce.py
suiteas/core/names.py
suiteas/core/path.py
suiteas/core/print.py
suiteas/core/rules.py
suiteas/core/run.py
suiteas/core/violations.py
suiteas/read/__init__.py
suiteas/read/codebase.py
suiteas/read/config.py
suiteas/read/file.py
suiteas/read/project.py
suiteas/read/pytest_file.py
suiteas/read/pytest_suite.py
suiteas-0.3.3.dist-info/LICENSE
suiteas-0.3.3.dist-info/METADATA
suiteas-0.3.3.dist-info/WHEEL
suiteas-0.3.3.dist-info/entry_points.txt
suiteas-0.3.3.dist-info/top_level.txt
suiteas-0.3.3.dist-info/RECORD
