Metadata-Version: 2.1
Name: suiteas
Version: 0.3.3
Summary: An opinionated testing suite organizer for pytest
Author-email: Nathan McDougall <nathan.j.mcdougall@gmail.com>
License: MIT
Project-URL: Source Code, https://github.com/nathanjmcdougall/suiteas
Project-URL: Bug Tracker, https://github.com/nathanjmcdougall/suiteas/issues
Keywords: pytest,test,testing,test suite,suite,sync,synchronize,pre-commit,boilerplate,skeleton
Classifier: Development Status :: 2 - Pre-Alpha
Classifier: Intended Audience :: Developers
Classifier: License :: OSI Approved :: MIT License
Classifier: Operating System :: OS Independent
Classifier: Programming Language :: Python
Classifier: Programming Language :: Python :: 3
Classifier: Programming Language :: Python :: 3 :: Only
Classifier: Programming Language :: Python :: 3.10
Classifier: Programming Language :: Python :: 3.11
Classifier: Programming Language :: Python :: 3.12
Classifier: Topic :: Software Development :: Testing
Classifier: Typing :: Typed
Requires-Python: >=3.10
License-File: LICENSE
Requires-Dist: pydantic >=2.4.2
Requires-Dist: tomli >=2.0.1
